ip2d-py/__init__.py
ip2d-py/__main__.py
ip2d-py/fun.py
ip2dpy/__init__.py
ip2dpy/__main__.py
ip2d_py-0.1.0.dist-info/LICENSE
ip2d_py-0.1.0.dist-info/METADATA
ip2d_py-0.1.0.dist-info/WHEEL
ip2d_py-0.1.0.dist-info/entry_points.txt
ip2d_py-0.1.0.dist-info/top_level.txt
ip2d_py-0.1.0.dist-info/RECORD
