Metadata-Version: 2.1
Name: ip2d-py
Version: 0.1.0
Summary: Convert IP addresses to integers on cli
Home-page: https://github.com/0xflotus/ip2d-py
Author: 0xflotus
Author-email: 0xflotus+pypi@gmail.com
License: MIT
Platform: UNKNOWN
Classifier: License :: OSI Approved :: MIT License
Classifier: Programming Language :: Python :: 3
Classifier: Programming Language :: Python :: 3.9
License-File: LICENSE
Requires-Dist: ipy2d (==0.1.0)
Requires-Dist: argparse
